byted_overpass_aurora_health_ai_consult/__init__.py
byted_overpass_aurora_health_ai_consult-0.0.1.dist-info/METADATA
byted_overpass_aurora_health_ai_consult-0.0.1.dist-info/WHEEL
byted_overpass_aurora_health_ai_consult-0.0.1.dist-info/top_level.txt
byted_overpass_aurora_health_ai_consult-0.0.1.dist-info/RECORD
